{
  "active": false,
  "connections": {},
  "createdAt": "2025-08-06T20:10:13.225Z",
  "id": "PRLPHanmDUeDgJaQ",
  "isArchived": false,
  "meta": null,
  "name": "AAA Master",
  "nodes": [
    {
      "parameters": {
        "content": "## AI Automation Agency Master Workflow",
        "height": 80,
        "width": 480,
        "color": 4
      },
      "type": "n8n-nodes-base.stickyNote",
      "position": [
        512,
        544
      ],
      "typeVersion": 1,
      "id": "f89dab12-8563-4a16-8f7d-6f211653288c",
      "name": "Sticky Note"
    }
  ],
  "pinData": {},
  "repo_name": "backup-n8n",
  "repo_owner": "gracp",
  "repo_path": "backups",
  "settings": {
    "executionOrder": "v1",
    "timezone": "America/Vancouver",
    "callerPolicy": "workflowsFromSameOwner"
  },
  "staticData": null,
  "tags": [],
  "triggerCount": 0,
  "updatedAt": "2025-08-06T20:13:17.557Z",
  "versionId": "9dd9b4a1-5367-45e0-bbdc-ba7945674858"
}